nazli/__init__.py
nazli/main.py
nazli/pixel_art.py
nazli-1.0.0.dist-info/LICENSE
nazli-1.0.0.dist-info/METADATA
nazli-1.0.0.dist-info/WHEEL
nazli-1.0.0.dist-info/entry_points.txt
nazli-1.0.0.dist-info/top_level.txt
nazli-1.0.0.dist-info/RECORD
