Metadata-Version: 2.2
Name: nazli
Version: 1.0.0
Summary: Present Characters as Pixel Emoji
Author-email: "Kamyar M.G." <kmgurmia@gmail.com>
Maintainer-email: "Kamyar M.G." <kmgurmia@gmail.com>
License: MIT License
Project-URL: Homepage, https://github.com/kamyarmg/nazli
Project-URL: Repository, https://github.com/kamyarmg/nazli
Project-URL: Issues, https://github.com/kamyarmg/nazli/issues
Project-URL: Changelog, https://github.com/kamyarmg/nazli/blob/master/CHANGELOG.rst
Keywords: emoji,python,string,cute,funny,NAZLI
Classifier: Development Status :: 1 - Planning
Classifier: Intended Audience :: Developers
Classifier: Topic :: Software Development :: Build Tools
Classifier: Topic :: File Formats :: JSON
Classifier: License :: OSI Approved :: MIT License
Classifier: Programming Language :: Python :: 3
Classifier: Programming Language :: Python :: 3.10
Classifier: Programming Language :: Python :: 3.11
Classifier: Programming Language :: Python :: 3.12
Classifier: Programming Language :: Python :: 3.13
Requires-Python: >=3.10
License-File: LICENSE
